pymanylinuxdemo/extension.cpython-36m-x86_64-linux-gnu.so
pymanylinuxdemo/__init__.py
pymanylinuxdemo/tests/test_extension.py
pymanylinuxdemo/tests/__init__.py
loganek_python_manylinux_demo-1.0.dist-info/LICENSE
loganek_python_manylinux_demo-1.0.dist-info/RECORD
loganek_python_manylinux_demo-1.0.dist-info/METADATA
loganek_python_manylinux_demo-1.0.dist-info/WHEEL
loganek_python_manylinux_demo-1.0.dist-info/top_level.txt
loganek_python_manylinux_demo.libs/libquadmath-30d679e1.so.0.0.0
loganek_python_manylinux_demo.libs/libblas-357956a1.so.3.4.2
loganek_python_manylinux_demo.libs/libgfortran-4fc760a1.so.3.0.0
